{"annotatable":{"parts":["s1v1","s2v1","s3v1","s4v1","s5v1","s6v1","s7v1","s8v1","s9v1","s10v1","s11v1","s12v1","s13v1"]},"anncomplete":true,"sources":[],"metas":{"m_82":{"value":"Low-risk","confidence":{"state":"pre-added","who":["user:katia-giacomino"],"prob":1}},"m_83":{"value":"Low-risk","confidence":{"state":"pre-added","who":["user:katia-giacomino"],"prob":1}},"m_84":{"value":"Low-risk","confidence":{"state":"pre-added","who":["user:katia-giacomino"],"prob":1}},"m_85":{"value":"Low-risk","confidence":{"state":"pre-added","who":["user:katia-giacomino"],"prob":1}},"m_86":{"value":"Some-concerns","confidence":{"state":"pre-added","who":["user:katia-giacomino"],"prob":1}},"m_35":{"value":"Some-concerns","confidence":{"state":"pre-added","who":["user:katia-giacomino"],"prob":1}}},"entities":[{"classId":"e_136","part":"s2v1","offsets":[{"start":240,"text":"Of  t h e s e ,  1  s u b j e c t   (4.2%)  w i t h d r e w   f r o m   t h e   s t u d y   f o r   p e r s o n a l   r e a s o n s ;"}],"coordinates":[{"x":"367.92","y":"101.31"},{"x":"345.34","y":"118.80"}],"confidence":{"state":"pre-added","who":["user:katia-giacomino"],"prob":1},"fields":{},"normalizations":{}},{"classId":"e_124","part":"s4v1","offsets":[{"start":3278,"text":"All  eligible  s u b j e c t s   p r o v i d e d  w r i t t e n   i n f o r m e d   c o n s e n t   t o   p a r t i c i p a t e ."}],"coordinates":[{"x":"272.88","y":"352.59"},{"x":"234.52","y":"370.08"}],"confidence":{"state":"pre-added","who":["user:katia-giacomino"],"prob":1},"fields":{},"normalizations":{}},{"classId":"e_114","part":"s4v1","offsets":[{"start":4139,"text":"S u b j e c t s   w e r e   r a n d o m i z e d ,   a c c o r d i n g   t o   a  c o m p u t e r - g e n e r a t e d   r a n d o m i z a -  t i o n   t a b l e   of s e q u e n c e s ,   t o   r e c e i v e   e i t h e r   t h e   t e s t *   o r   r e f e r e n c e  ~ f o r m u l a t i o n  of e n a l a p r i l   (20-mg t a b l e t )   a t  s t u d y  p e r i o d   1 a n d   t h e  o p p o s i t e   f o r m u l a t i o n  a t  s t u d y  p e r i o d   2."}],"coordinates":[{"x":"62.88","y":"460.35"},{"x":"91.06","y":"501.84"}],"confidence":{"state":"pre-added","who":["user:katia-giacomino"],"prob":1},"fields":{},"normalizations":{}},{"classId":"e_109","part":"s4v1","offsets":[{"start":4139,"text":"S u b j e c t s   w e r e   r a n d o m i z e d ,   a c c o r d i n g   t o   a  c o m p u t e r - g e n e r a t e d   r a n d o m i z a -  t i o n   t a b l e   of s e q u e n c e s ,"}],"coordinates":[{"x":"62.88","y":"460.35"},{"x":"157.55","y":"477.84"}],"confidence":{"state":"pre-added","who":["user:katia-giacomino"],"prob":1},"fields":{},"normalizations":{}},{"classId":"e_124","part":"s4v1","offsets":[{"start":4326,"text":"t o   r e c e i v e   e i t h e r   t h e   t e s t *   o r   r e f e r e n c e  ~ f o r m u l a t i o n  of e n a l a p r i l   (20-mg t a b l e t )   a t  s t u d y  p e r i o d   1 a n d   t h e  o p p o s i t e   f o r m u l a t i o n  a t  s t u d y  p e r i o d   2."}],"coordinates":[{"x":"162.00","y":"472.35"},{"x":"91.06","y":"501.84"}],"confidence":{"state":"pre-added","who":["user:katia-giacomino"],"prob":1},"fields":{},"normalizations":{}},{"classId":"e_129","part":"s4v1","offsets":[{"start":4805,"text":"v o l u n t e e r s   r e c e i v e d   t h e   m e d i c a t i o n  w i t h   150  mL of  w a t e r   at  r o o m   t e m p e r a t u r e   b y   a  n u r s e"}],"coordinates":[{"x":"244.56","y":"508.35"},{"x":"298.35","y":"525.84"}],"confidence":{"state":"pre-added","who":["user:katia-giacomino"],"prob":1},"fields":{},"normalizations":{}},{"classId":"e_186","part":"s4v1","offsets":[{"start":4987,"text":"Blood s a m p l e s  of - 1 0   mL e a c h  w e r e   d r a w n  b y  a n u r s e   a t   15 t i m e  p o i n t s :  b a s e l i n e  ( i m m e d i a t e l y   b e f o r e   s t u d y   d r u g   a d m i n i s t r a t i o n ) ;   30,  45,  60,  75,  105,  135,  180,"}],"coordinates":[{"x":"50.88","y":"556.35"},{"x":"410.10","y":"573.60"}],"confidence":{"state":"pre-added","who":["user:katia-giacomino"],"prob":1},"fields":{},"normalizations":{}},{"classId":"e_186","part":"s5v1","offsets":[{"start":31,"text":"195,  a n d   225  m i n u t e s ;   a n d   5,  8,  12,  24,  a n d   36  h o u r s   a f t e r   s t u d y   d r u g   a d m i n i s -  t r a t i o n .   S a m p l e s   w e r e   c e n t r i f u g e d   at  3000  r p m   for  10  m i n u t e s   ( a t   4°C),  a n d   t h e  o b t a i n e d   p l a s m a   s a m p l e s   w e r e   s e p a r a t e d   in  t w o   1.5-mL a l i q u o t s   a n d   s t o r e d   in s u i t a b l y  l a b e l e d ,   t i g h t l y  s e a l e d   t u b e s   at -30°C.  After 24 h o u r s ,   t h e  s a m p l e s  w e r e  t r a n s f e r r e d   t o   -80°C.  V o l u n t e e r s   r e m a i n e d   u n d e r   m e d i c a l   s u p e r v i s i o n   a t   t h e  s t u d y   c e n t e r   u n t i l   12  h o u r s   a f t e r   s t u d y   d r u g   a d m i n i s t r a t i o n ,   a n d   r e t u r n e d   at 24  a n d   36  h o u r s   a f t e r   a d m i n i s t r a t i o n  for  t h e   l a s t   e x t r a c t i o n s .  A n a l y t i c a l  d e t e r m i n a t i o n  of p l a s m a  d r u g  a n d  m e t a b o l i t e  c o n c e n t r a t i o n s  w e r e  p e r f o r m e d  b y  MCC AnaHtica S.A. ( B a r c e l o n a ,   Spain)  a n d   f o l l o w e d  a n   a c i d  s o l i d -  liquid  e x t r a c t i o n   w i t h   a  r e v e r s e d - p h a s e   h i g h - p r e s s u r e   liquid  c h r o m a t o g r a p h y  s e p a r a t i o n   a n d   m a s s   s p e c t r o m e t r y   d e t e c t o r .   Lisinopril w a s   u s e d   as  a n   i n t e r n a l  s t a n d a r d .   T h e   m e t h o d   of  a n a l y s i s   w a s   v a l i d a t e d   u n d e r   t h e   p r i n c i p l e s   of  Good L a b o r a t o r y   P r a c t i c e   t h r o u g h   t h e   f o l l o w i n g   p a r a m e t e r s :   l i n e a r i t y ,   p r e c i s i o n ,  i n t r a - a s s a y  a n d   i n t e r a s s a y  a c c u r a c y ,   limit of q u a n t i f i c a t i o n  (LOQ),  v a l i d a t i o n  of t h e   d i l u t i o n  f a c t o r ,  s p e c i f i c i t y ,  s t a b i l i t y ,  a n d  r e c o v e r y ."}],"coordinates":[{"x":"51.84","y":"89.31"},{"x":"293.04","y":"262.32"}],"confidence":{"state":"pre-added","who":["user:katia-giacomino"],"prob":1},"fields":{},"normalizations":{}},{"classId":"e_211","part":"s5v1","offsets":[{"start":1000,"text":"A n a l y t i c a l  d e t e r m i n a t i o n  of p l a s m a  d r u g  a n d  m e t a b o l i t e  c o n c e n t r a t i o n s  w e r e  p e r f o r m e d  b y  MCC AnaHtica S.A. ( B a r c e l o n a ,   Spain)  a n d   f o l l o w e d  a n   a c i d  s o l i d -  liquid  e x t r a c t i o n   w i t h   a  r e v e r s e d - p h a s e   h i g h - p r e s s u r e   liquid  c h r o m a t o g r a p h y  s e p a r a t i o n   a n d   m a s s   s p e c t r o m e t r y   d e t e c t o r ."}],"coordinates":[{"x":"62.64","y":"173.07"},{"x":"252.87","y":"214.56"}],"confidence":{"state":"pre-added","who":["user:katia-giacomino"],"prob":1},"fields":{},"normalizations":{}},{"classId":"e_190","part":"s5v1","offsets":[{"start":2094,"text":"T h e   a n a l y t i c a l  p a r t   of t h e  s t u d y  w a s   d e v e l o p e d   b l i n d l y ."}],"coordinates":[{"x":"296.40","y":"256.83"},{"x":"185.36","y":"274.32"}],"confidence":{"state":"pre-added","who":["user:katia-giacomino"],"prob":1},"fields":{},"normalizations":{}},{"classId":"e_122","part":"s6v1","offsets":[{"start":1683,"text":"T w e n t y - f o u r   w h i t e   h e a l t h y   v o l u n t e e r s   w e r e   i n c l u d e d   in  t h e   s t u d y   (12  m e n ,  12 w o m e n ;  m e a n   [SD] age, 22.8  [2.2]  y e a r s   [range,  19-30 y e a r s ] ;  m e a n   [SD] b o d y  w e i g h t ,   65.1  [12.4]  kg  [men,  75.3  (9.1)  kg;  w o m e n ,   54.9  (4.6)  kg];  m e a n   [SD] h e i g h t ,   173.0  [10.2]  c m   [men,  182.7  (4.6)  cm;  w o m e n ,   163.9  (3.6)  c m ] ) ."}],"coordinates":[{"x":"50.88","y":"280.83"},{"x":"385.76","y":"322.32"}],"confidence":{"state":"pre-added","who":["user:katia-giacomino"],"prob":1},"fields":{},"normalizations":{}},{"classId":"e_158","part":"s6v1","offsets":[{"start":1683,"text":"T w e n t y - f o u r   w h i t e   h e a l t h y   v o l u n t e e r s   w e r e   i n c l u d e d   in  t h e   s t u d y   (12  m e n ,  12 w o m e n ;  m e a n   [SD] age, 22.8  [2.2]  y e a r s   [range,  19-30 y e a r s ] ;  m e a n   [SD] b o d y  w e i g h t ,   65.1  [12.4]  kg  [men,  75.3  (9.1)  kg;  w o m e n ,   54.9  (4.6)  kg];  m e a n   [SD] h e i g h t ,   173.0  [10.2]  c m   [men,  182.7  (4.6)  cm;  w o m e n ,   163.9  (3.6)  c m ] ) .   One s u b j e c t   (4.2%)  w i t h d r e w   b e t w e e n   s t u d y   p e r i o d s   f o r   p e r s o n a l   r e a s o n s .   T h e   re- s u i t s   of  23  s u b j e c t s   w e r e   i n c l u d e d   in  t h e   PK  a n a l y s i s ."}],"coordinates":[{"x":"50.88","y":"280.83"},{"x":"296.08","y":"346.32"}],"confidence":{"state":"pre-added","who":["user:katia-giacomino"],"prob":1},"fields":{},"normalizations":{}},{"classId":"e_181","part":"s6v1","offsets":[{"start":3239,"text":"P h a r m a c o k i n e t i c  Analysis"}],"coordinates":[{"x":"51.12","y":"459.61"},{"x":"179.89","y":"465.84"}],"confidence":{"state":"pre-added","who":["user:katia-giacomino"],"prob":1},"fields":{},"normalizations":{}}],"relations":[]}