{"annotatable":{"parts":["s1v1","s2v1","s3v1","s4v1","s5v1","s6v1","s7v1","s8v1","s9v1","s10v1","s11v1","s12v1","s13v1","s14v1","s15v1","s16v1","s17v1","s18v1","s19v1","s20v1"]},"anncomplete":true,"sources":[],"metas":{"m_82":{"value":"Low-risk","confidence":{"state":"pre-added","who":["user:rahel-caliesch"],"prob":1}},"m_83":{"value":"Low-risk","confidence":{"state":"pre-added","who":["user:rahel-caliesch"],"prob":1}},"m_84":{"value":"Low-risk","confidence":{"state":"pre-added","who":["user:rahel-caliesch"],"prob":1}},"m_85":{"value":"Low-risk","confidence":{"state":"pre-added","who":["user:rahel-caliesch"],"prob":1}},"m_86":{"value":"Low-risk","confidence":{"state":"pre-added","who":["user:rahel-caliesch"],"prob":1}},"m_35":{"value":"Low-risk","confidence":{"state":"pre-added","who":["user:rahel-caliesch"],"prob":1}}},"entities":[{"classId":"e_135","part":"s1v1","offsets":[{"start":1297,"text":"Fourteen patients received L4-5 primary dorsal rami and S1-3 lateralbranch radiofrequency denervation"}],"coordinates":[{"x":"233.06","y":"445.15"},{"x":"247.95","y":"463.72"}],"confidence":{"state":"pre-added","who":["user:rahel-caliesch"],"prob":1},"fields":{},"normalizations":{}},{"classId":"e_135","part":"s1v1","offsets":[{"start":1465,"text":"and 14 patients received the local anesthetic block followed by placebo denervation"}],"coordinates":[{"x":"135.03","y":"469.15"},{"x":"467.58","y":"475.72"}],"confidence":{"state":"pre-added","who":["user:rahel-caliesch"],"prob":1},"fields":{},"normalizations":{}},{"classId":"e_107","part":"s3v1","offsets":[{"start":1362,"text":"Studypatients were randomized in a 1:1 ratio to receive either true or placebo denervation. A researchnurse not involved in patient care performed randomization in blocks of 4 via pre-sealedenvelopes at each institution"}],"coordinates":[{"x":"492.46","y":"286.99"},{"x":"263.60","y":"329.56"}],"confidence":{"state":"pre-added","who":["user:rahel-caliesch"],"prob":1},"fields":{},"normalizations":{}},{"classId":"e_190","part":"s3v1","offsets":[{"start":1410,"text":"receive either true or placebo denervation."}],"coordinates":[{"x":"312.91","y":"298.99"},{"x":"478.02","y":"305.56"}],"confidence":{"state":"pre-added","who":["user:rahel-caliesch"],"prob":1},"fields":{},"normalizations":{}},{"classId":"e_185","part":"s3v1","offsets":[{"start":1410,"text":"receive either true or placebo denervation"}],"coordinates":[{"x":"312.91","y":"298.99"},{"x":"475.52","y":"305.56"}],"confidence":{"state":"pre-added","who":["user:rahel-caliesch"],"prob":1},"fields":{},"normalizations":{}},{"classId":"e_113","part":"s3v1","offsets":[{"start":1454,"text":"A researchnurse not involved in patient care performed randomization in blocks of 4 via pre-sealedenvelopes at each institution"}],"coordinates":[{"x":"479.77","y":"298.99"},{"x":"263.60","y":"329.56"}],"confidence":{"state":"pre-added","who":["user:rahel-caliesch"],"prob":1},"fields":{},"normalizations":{}},{"classId":"e_125","part":"s3v1","offsets":[{"start":2842,"text":"ensure blinding"}],"coordinates":[{"x":"415.21","y":"478.99"},{"x":"477.15","y":"485.56"}],"confidence":{"state":"pre-added","who":["user:rahel-caliesch"],"prob":1},"fields":{},"normalizations":{}},{"classId":"e_190","part":"s3v1","offsets":[{"start":2842,"text":"ensure blinding"}],"coordinates":[{"x":"415.21","y":"478.99"},{"x":"477.15","y":"485.56"}],"confidence":{"state":"pre-added","who":["user:rahel-caliesch"],"prob":1},"fields":{},"normalizations":{}},{"classId":"e_128","part":"s4v1","offsets":[{"start":601,"text":"In the control group, electrodes were similarly positioned, electrostimulation was performedin an identical manner, and 0.5 ml of lidocaine 2% was administered, but no current wasadministered"}],"coordinates":[{"x":"150.00","y":"156.80"},{"x":"201.66","y":"187.37"}],"confidence":{"state":"pre-added","who":["user:rahel-caliesch"],"prob":1},"fields":{},"normalizations":{}},{"classId":"e_125","part":"s4v1","offsets":[{"start":608,"text":"control group, electrodes were similarly positioned, electrostimulation was performedin an identical manner, and 0.5 ml of lidocaine 2% was administered, but no current wasadministered"}],"coordinates":[{"x":"175.55","y":"156.80"},{"x":"201.66","y":"187.37"}],"confidence":{"state":"pre-added","who":["user:rahel-caliesch"],"prob":1},"fields":{},"normalizations":{}},{"classId":"e_180","part":"s4v1","offsets":[{"start":3116,"text":"The primary outcome measure was a 0–10 NRS pain score, which reflected the average painexperienced by the patient for 10 days prior to follow-up"}],"coordinates":[{"x":"150.00","y":"552.90"},{"x":"376.90","y":"571.47"}],"confidence":{"state":"pre-added","who":["user:rahel-caliesch"],"prob":1},"fields":{},"normalizations":{}},{"classId":"e_185","part":"s4v1","offsets":[{"start":3116,"text":"The primary outcome measure was a 0–10 NRS pain score, which reflected the average painexperienced by the patient for 10 days prior to follow-up."}],"coordinates":[{"x":"150.00","y":"552.90"},{"x":"379.40","y":"571.47"}],"confidence":{"state":"pre-added","who":["user:rahel-caliesch"],"prob":1},"fields":{},"normalizations":{}},{"classId":"e_204","part":"s5v1","offsets":[{"start":477,"text":"The Shapiro-Wilk W test for normal data was performed on continuous outcomemeasures."}],"coordinates":[{"x":"171.66","y":"168.90"},{"x":"189.71","y":"187.47"}],"confidence":{"state":"pre-added","who":["user:rahel-caliesch"],"prob":1},"fields":{},"normalizations":{}},{"classId":"e_215","part":"s5v1","offsets":[{"start":655,"text":"Continuous variables are reported as mean and standard deviation or median andinterquartile range."}],"coordinates":[{"x":"192.49","y":"192.90"},{"x":"226.09","y":"211.47"}],"confidence":{"state":"pre-added","who":["user:rahel-caliesch"],"prob":1},"fields":{},"normalizations":{}},{"classId":"e_215","part":"s5v1","offsets":[{"start":655,"text":"Continuous variables are reported as mean and standard deviation"}],"coordinates":[{"x":"192.49","y":"192.90"},{"x":"455.77","y":"199.47"}],"confidence":{"state":"pre-added","who":["user:rahel-caliesch"],"prob":1},"fields":{},"normalizations":{}},{"classId":"e_204","part":"s5v1","offsets":[{"start":821,"text":"Comparisons between the initial radiofrequency treatment group and the placebo group weremade with unpaired t-tests or Mann-Whitney U test."}],"coordinates":[{"x":"150.00","y":"216.90"},{"x":"358.86","y":"235.47"}],"confidence":{"state":"pre-added","who":["user:rahel-caliesch"],"prob":1},"fields":{},"normalizations":{}},{"classId":"e_120","part":"s5v1","offsets":[{"start":1505,"text":"Demographic (including active duty status) and clinicalcharacteristics were balanced between the radiofrequency denervation treatment and controlgroup"}],"coordinates":[{"x":"292.46","y":"362.98"},{"x":"173.33","y":"393.55"}],"confidence":{"state":"pre-added","who":["user:rahel-caliesch"],"prob":1},"fields":{},"normalizations":{}},{"classId":"e_210","part":"s5v1","offsets":[{"start":2702,"text":"A significant difference in the primary outcome, NRS pain score, was detected between the"}],"coordinates":[{"x":"150.00","y":"569.08"},{"x":"515.75","y":"575.65"}],"confidence":{"state":"pre-added","who":["user:rahel-caliesch"],"prob":1},"fields":{},"normalizations":{}},{"classId":"e_210","part":"s5v1","offsets":[{"start":2878,"text":"treatment group had significantly lower NRS scores than the placebo group"}],"coordinates":[{"x":"150.00","y":"593.08"},{"x":"451.62","y":"599.65"}],"confidence":{"state":"pre-added","who":["user:rahel-caliesch"],"prob":1},"fields":{},"normalizations":{}},{"classId":"e_210","part":"s5v1","offsets":[{"start":2878,"text":"treatment group had significantly lower NRS scores than the placebo group (2.4 ± 2.0; range0–8 vs. 6.3 ± 2.4; range 2–10, p<0.001, respectively)"}],"coordinates":[{"x":"150.00","y":"593.08"},{"x":"361.30","y":"611.65"}],"confidence":{"state":"pre-added","who":["user:rahel-caliesch"],"prob":1},"fields":{},"normalizations":{}},{"classId":"e_210","part":"s5v1","offsets":[{"start":2952,"text":"(2.4 ± 2.0; range"}],"coordinates":[{"x":"454.12","y":"593.08"},{"x":"520.43","y":"599.65"}],"confidence":{"state":"pre-added","who":["user:rahel-caliesch"],"prob":1},"fields":{},"normalizations":{}},{"classId":"e_215","part":"s5v1","offsets":[{"start":2969,"text":"0–8 vs. 6.3 ± 2.4; range 2–10, p<0.001, respectively)"}],"coordinates":[{"x":"150.00","y":"605.08"},{"x":"361.30","y":"611.65"}],"confidence":{"state":"pre-added","who":["user:rahel-caliesch"],"prob":1},"fields":{},"normalizations":{}},{"classId":"e_210","part":"s5v1","offsets":[{"start":3523,"text":"uthor Manuscript NIH-PA A"}],"coordinates":[{"x":"145.94","y":"580.99"},{"x":"359.30","y":"589.16"}],"confidence":{"state":"pre-added","who":["user:rahel-caliesch"],"prob":1},"fields":{},"normalizations":{}},{"classId":"e_210","part":"s5v1","offsets":[{"start":3548,"text":"uthor Manus"}],"coordinates":[{"x":"359.31","y":"580.99"},{"x":"426.00","y":"589.16"}],"confidence":{"state":"pre-added","who":["user:rahel-caliesch"],"prob":1},"fields":{},"normalizations":{}},{"classId":"e_149","part":"s12v1","offsets":[{"start":9,"text":"CONSORT chart showing progression of subjects in study arms"}],"coordinates":[{"x":"150.00","y":"590.62"},{"x":"406.65","y":"597.19"}],"confidence":{"state":"pre-added","who":["user:rahel-caliesch"],"prob":1},"fields":{},"normalizations":{}},{"classId":"e_158","part":"s12v1","offsets":[{"start":9,"text":"CONSORT chart showing progression of subjects in study arms"}],"coordinates":[{"x":"150.00","y":"590.62"},{"x":"406.65","y":"597.19"}],"confidence":{"state":"pre-added","who":["user:rahel-caliesch"],"prob":1},"fields":{},"normalizations":{}},{"classId":"e_149","part":"s12v1","offsets":[{"start":237,"text":"Author M"}],"coordinates":[{"x":"137.93","y":"580.99"},{"x":"186.62","y":"589.16"}],"confidence":{"state":"pre-added","who":["user:rahel-caliesch"],"prob":1},"fields":{},"normalizations":{}},{"classId":"e_158","part":"s12v1","offsets":[{"start":238,"text":"uthor M"}],"coordinates":[{"x":"145.94","y":"580.99"},{"x":"186.62","y":"589.16"}],"confidence":{"state":"pre-added","who":["user:rahel-caliesch"],"prob":1},"fields":{},"normalizations":{}}],"relations":[]}